volttron/auth/zap/__init__.py
volttron/auth/zap/credential_store.py
volttron/auth/zap/credentials_creator.py
volttron/auth/zap/zap_authenticator.py
volttron/messagebus/zmq/__init__.py
volttron/messagebus/zmq/client.py
volttron/messagebus/zmq/config.py
volttron/messagebus/zmq/credentials_creator.py
volttron/messagebus/zmq/federation_bridge.py
volttron/messagebus/zmq/green.py
volttron/messagebus/zmq/keystore.py
volttron/messagebus/zmq/monitor.py
volttron/messagebus/zmq/router/__init__.py
volttron/messagebus/zmq/router/base_router.py
volttron/messagebus/zmq/router/green_router.py
volttron/messagebus/zmq/router/router.py
volttron/messagebus/zmq/router/servicepeer.py
volttron/messagebus/zmq/routing/__init__.py
volttron/messagebus/zmq/routing/external_rpc_service.py
volttron/messagebus/zmq/routing/pubsub_service.py
volttron/messagebus/zmq/routing/routing_service.py
volttron/messagebus/zmq/routing/zmq_proxy_router.py
volttron/messagebus/zmq/serialize_frames.py
volttron/messagebus/zmq/server_auth.py
volttron/messagebus/zmq/socket.py
volttron/messagebus/zmq/tracking.py
volttron/messagebus/zmq/zmq_connection.py
volttron/messagebus/zmq/zmq_core.py
volttron/py.typed
volttron_lib_zmq-2.0.0rc7.dist-info/LICENSE
volttron_lib_zmq-2.0.0rc7.dist-info/METADATA
volttron_lib_zmq-2.0.0rc7.dist-info/WHEEL
volttron_lib_zmq-2.0.0rc7.dist-info/RECORD
