Metadata-Version: 2.3
Name: volttron-lib-zmq
Version: 2.0.0rc7
Summary: VOLTTRON zmq message bus implementation
License: Apache-2.0
Author: C. Allwardt
Author-email: 3979063+craig8@users.noreply.github.com
Requires-Python: >=3.10,<4.0
Classifier: Intended Audience :: Developers
Classifier: Intended Audience :: Information Technology
Classifier: Intended Audience :: Other Audience
Classifier: Intended Audience :: Science/Research
Classifier: License :: OSI Approved :: Apache Software License
Classifier: Programming Language :: Python :: 3
Classifier: Programming Language :: Python :: 3.10
Classifier: Programming Language :: Python :: 3.11
Classifier: Programming Language :: Python :: 3.12
Classifier: Programming Language :: Python :: 3.13
Classifier: Programming Language :: Python :: 3 :: Only
Requires-Dist: msgpack-python (>=0.5.6,<0.6.0)
Requires-Dist: pyzmq (>=25.1.2,<26.0.0)
Requires-Dist: volttron-core (>=2.0.0rc13)
Project-URL: Homepage, https://github.com/eclipse-volttron/volttron-lib-zmq
Project-URL: Repository, https://github.com/eclipse-volttron/volttron-lib-zmq
